mulsi/__init__.py
mulsi/adversarial.py
mulsi/clf.py
mulsi/hook.py
mulsi/preprocess.py
mulsi/probe.py
mulsi/reader.py
mulsi/representation.py
mulsi/wrapper.py
mulsi-0.1.2.dist-info/LICENSE
mulsi-0.1.2.dist-info/METADATA
mulsi-0.1.2.dist-info/WHEEL
mulsi-0.1.2.dist-info/RECORD
