Metadata-Version: 2.1
Name: mulsi
Version: 0.1.2
Summary: Safe inference using representation engineering.
License: MIT
Author: Yoann Poupart
Author-email: yoann.poupart@ens-lyon.org
Requires-Python: >=3.9,<4.0
Classifier: License :: OSI Approved :: MIT License
Classifier: Programming Language :: Python :: 3
Classifier: Programming Language :: Python :: 3.9
Classifier: Programming Language :: Python :: 3.10
Classifier: Programming Language :: Python :: 3.11
Requires-Dist: datasets[scripts] (>=2.18.0,<3.0.0)
Requires-Dist: einops (>=0.7.0,<0.8.0)
Requires-Dist: python-semantic-release (>=9.6.0,<10.0.0)
Requires-Dist: tensordict (>=0.3.0,<0.4.0)
Requires-Dist: torch (>=2.1.2,<3.0.0)
Requires-Dist: torchvision (>=0.17.0,<0.18.0)
Requires-Dist: transformers (>=4.37.2,<5.0.0)
Requires-Dist: typeguard (>=4.1.5,<5.0.0)
Requires-Dist: wandb[scripts] (>=0.16.5,<0.17.0)
